{"thingId": "s3i:d1ed48ca-cf69-4ac6-99eb-8b1b025ba43a", "policyId": "s3i:d1ed48ca-cf69-4ac6-99eb-8b1b025ba43a", "attributes": {"class": "ml40::Thing", "name": "my_harvester", "roles": [{"class": "fml40::Harvester"}], "features": [{"class": "fml40::ProvidesProductionData"}, {"class": "fml40::AcceptsFellingJobs"}, {"class": "ml40::Composite", "targets": [{"class": "ml40::Thing", "name": "my_engine", "roles": [{"class": "ml40::Engine"}], "features": [{"class": "ml40::RotationalSpeed", "rpm": 2005}]}, {"class": "ml40::Thing", "name": "my_bord_computer", "roles": [{"class": "ml40::MachineUI"}], "features": []}]}]}}